[
  {
    "section": "section:1",
    "title": "Abstract"
  },
  {
    "section": "section:1",
    "title": "Background"
  },
  {
    "section": "section:1",
    "title": "Patients and Methods"
  },
  {
    "section": "section:2",
    "title": "Patient population"
  },
  {
    "section": "section:2",
    "title": "Study design"
  },
  {
    "section": "section:2",
    "title": "Safety and efficacy"
  },
  {
    "section": "section:2",
    "title": "Pharmacokinetics"
  },
  {
    "section": "section:2",
    "title": "Pharmacodynamics"
  },
  {
    "section": "section:1",
    "title": "Results"
  },
  {
    "section": "section:2",
    "title": "Dose escalation and MTD"
  },
  {
    "section": "section:2",
    "title": "Safety"
  },
  {
    "section": "section:2",
    "title": "Pharmacokinetic analysis"
  },
  {
    "section": "section:2",
    "title": "Efficacy"
  },
  {
    "section": "section:2",
    "title": "Pharmacodynamic analysis"
  },
  {
    "section": "section:1",
    "title": "Discussion"
  },
  {
    "section": "section:1",
    "title": "References"
  },
  {
    "section": "section:1",
    "title": "Figure 1"
  },
  {
    "section": "section:1",
    "title": "Figure 2"
  },
  {
    "section": "section:1",
    "title": "Table 1"
  },
  {
    "section": "section:1",
    "title": "Table 2"
  },
  {
    "section": "section:1",
    "title": "Table 3"
  },
  {
    "section": "section:1",
    "title": "Table 4"
  }
]